llm_kit_pro/__init__.py
llm_kit_pro/core/__init__.py
llm_kit_pro/core/base.py
llm_kit_pro/core/exceptions.py
llm_kit_pro/core/helpers/__init__.py
llm_kit_pro/core/helpers/file_url_to_llm_file.py
llm_kit_pro/core/helpers/json.py
llm_kit_pro/core/inputs.py
llm_kit_pro/core/registry.py
llm_kit_pro/core/types.py
llm_kit_pro/outputs/__init__.py
llm_kit_pro/providers/__init__.py
llm_kit_pro/providers/anthropic/__init__.py
llm_kit_pro/providers/anthropic/client.py
llm_kit_pro/providers/anthropic/config.py
llm_kit_pro/providers/anthropic/utils.py
llm_kit_pro/providers/bedrock/__init__.py
llm_kit_pro/providers/bedrock/adapters/base.py
llm_kit_pro/providers/bedrock/adapters/claude.py
llm_kit_pro/providers/bedrock/adapters/llama.py
llm_kit_pro/providers/bedrock/adapters/titan.py
llm_kit_pro/providers/bedrock/client.py
llm_kit_pro/providers/bedrock/config.py
llm_kit_pro/providers/bedrock/constants.py
llm_kit_pro/providers/gemini/__init__.py
llm_kit_pro/providers/gemini/client.py
llm_kit_pro/providers/gemini/config.py
llm_kit_pro/providers/openai/__init__.py
llm_kit_pro/providers/openai/client.py
llm_kit_pro/providers/openai/config.py
llm_kit_pro/settings.py
llm_kit_pro/utils/__init__.py
llm_kit_pro/version.py
llm_kit_pro-0.4.5.dist-info/METADATA
llm_kit_pro-0.4.5.dist-info/WHEEL
llm_kit_pro-0.4.5.dist-info/licenses/LICENSE
llm_kit_pro-0.4.5.dist-info/RECORD
