Metadata-Version: 2.4
Name: llm-kit-pro
Version: 0.4.5
Summary: A unified toolkit for working with multiple LLM providers
License: MIT
License-File: LICENSE
Keywords: llm,ai,openai,gemini,anthropic,language-models,async
Author: Preetam Raj
Requires-Python: >=3.11,<4.0
Classifier: Development Status :: 3 - Alpha
Classifier: Intended Audience :: Developers
Classifier: License :: OSI Approved :: MIT License
Classifier: Programming Language :: Python :: 3
Classifier: Programming Language :: Python :: 3.11
Classifier: Programming Language :: Python :: 3.12
Classifier: Programming Language :: Python :: 3.13
Classifier: Programming Language :: Python :: 3.14
Classifier: Topic :: Scientific/Engineering :: Artificial Intelligence
Classifier: Topic :: Software Development :: Libraries :: Python Modules
Provides-Extra: anthropic
Provides-Extra: bedrock
Provides-Extra: gemini
Provides-Extra: openai
Requires-Dist: anthropic (>=0.75.0,<0.76.0) ; extra == "anthropic"
Requires-Dist: boto3 (>=1.42.14,<2.0.0) ; extra == "bedrock"
Requires-Dist: google-genai (>=1.0.0,<2.0.0) ; extra == "gemini"
Requires-Dist: httpx (>=0.28.1)
Requires-Dist: json-repair (>=0.55.0,<0.56.0)
Requires-Dist: openai (>=2.14.0,<3.0.0) ; extra == "openai"
Requires-Dist: pydantic (>=2.0,<2.13)
Requires-Dist: pydantic-settings (>=2.12.0,<3.0.0)
